ntwrk/__init__.py
ntwrk-1.0.2.dist-info/LICENSE
ntwrk-1.0.2.dist-info/METADATA
ntwrk-1.0.2.dist-info/WHEEL
ntwrk-1.0.2.dist-info/top_level.txt
ntwrk-1.0.2.dist-info/RECORD
