Metadata-Version: 2.1
Name: ntwrk
Version: 1.0.2
Summary: Sophisticate Graph
Home-page: https://pypi.org/project/ntwrk/
Author: khiat Mohammed Abderrezzak
Author-email: khiat.dev@gmail.com
License: MIT
Keywords: graph
Classifier: Programming Language :: Python :: 3
Classifier: Operating System :: OS Independent
Classifier: License :: OSI Approved :: MIT License
Requires-Python: >=3.6
License-File: LICENSE
Requires-Dist: hashtbl (>=1.0.5)
